arbitrary_dateparser/__init__.py
arbitrary_dateparser/dateparser.py
arbitrary_dateparser-0.0.4.dist-info/LICENSE
arbitrary_dateparser-0.0.4.dist-info/METADATA
arbitrary_dateparser-0.0.4.dist-info/WHEEL
arbitrary_dateparser-0.0.4.dist-info/top_level.txt
arbitrary_dateparser-0.0.4.dist-info/RECORD
