Metadata-Version: 2.1
Name: arbitrary-dateparser
Version: 0.0.4
Summary: Date parsing for arbitrary strings!
Home-page: https://github.com/nottheswimmer/arbitrary-dateparser
Author: Michael Phelps
Author-email: michael.phelps@cpcc.edu
License: MIT
Platform: UNKNOWN
Classifier: Development Status :: 3 - Alpha
Classifier: Programming Language :: Python :: 3
Classifier: License :: OSI Approved :: MIT License
Classifier: Operating System :: OS Independent
Requires-Python: >=3, <4
Requires-Dist: pendulum (==2.0.5)
